following_checker/__init__.py
following_checker/__main__.py
following_checker/extract_profile.py
following_checker-0.2.0.dist-info/WHEEL
following_checker-0.2.0.dist-info/METADATA
following_checker-0.2.0.dist-info/RECORD
