Metadata-Version: 2.1
Name: following-checker
Version: 0.2.0
Summary: 
Author: LeieXoyo
Author-email: gen@gen.li
Requires-Python: >=3.9,<4.0
Classifier: Programming Language :: Python :: 3
Classifier: Programming Language :: Python :: 3.10
Classifier: Programming Language :: Python :: 3.9
Requires-Dist: PySocks (>=1.7.1,<2.0.0)
Requires-Dist: requests (>=2.27.1,<3.0.0)
